{
    "title": [
        {
            "id": "tt17351924",
            "name": "Saltburn",
            "image": "https://m.media-amazon.com/images/M/MV5BM2NmMDQ1ZWEtNDU4OS00MGIxLWEyMGMtMTM2YmFkYzNhYmMxXkEyXkFqcGdeQXVyMTM1NjM2ODg1._V1_.jpg",
            "description": "A student at Oxford University finds himself drawn into the world of a charming and aristocratic classmate, who invites him to his eccentric familys sprawling estate for a summer never to be forgotten.",
            "review": {
                "reviewRating": {
                    "worstRating": 1,
                    "bestRating": 10,
                    "ratingValue": 7.0
                }
            },
            "genre": [
                "Comedy",
                "Drama",
                "Thriller"
            ],
            "trailer": {
                "name": "Official Trailer",
                "url": "https://www.youtube.com/embed/lALMdJf6UUE?si=755f4GvFl77r4-hJ",
                "description": "A student at Oxford University finds himself drawn into the world of a charming and aristocratic classmate, who invites him to his eccentric familys sprawling estate for a summer never to be forgotten.",
                "duration": "PT2M30S",
                "uploadDate": "2023-10-19T15:16:56.458Z"
            },
            "actor": [
                {
                    "id": "nm4422686",
                    "name": "Barry Keoghan"
                },
                {
                    "id": "nm8624059",
                    "name": "Jacob Elordi"
                },
                {
                    "id": "nm0683253",
                    "name": "Rosamund Pike"
                }
            ],
            "director": [
                {
                    "id": "nm2193504",
                    "name": "Emerald Fennell"
                }
            ],
            "creator": [
                {
                    "id": "nm2193504",
                    "name": "Emerald Fennell"
                }
            ]
        },
        {
            "id": "tt5611024",
            "name": "Fool Me Once",
            "image": "https://m.media-amazon.com/images/M/MV5BODViYWFhMDItYzIxYi00ZmE5LWI0NmUtYzI3MjZiZjMzNmEyXkEyXkFqcGdeQXVyMTMzNzIyNDc1._V1_.jpg",
            "description": "Widowed mum Maya is disturbed by an image of her late husband captured on her toddlers nanny cam.",
            "review": {
                "reviewRating": {
                    "worstRating": 1,
                    "bestRating": 10,
                    "ratingValue": 7
                }
            },
            "genre": [
                "Crime",
                "Drama",
                "Mystery"
            ],
            "actor": [
                {
                    "id": "nm2882021",
                    "name": "Michelle Keegan"
                },
                {
                    "id": "nm2253821",
                    "name": "Adeel Akhtar"
                },
                {
                    "id": "nm0035514",
                    "name": "Richard Armitage"
                }
            ],
            "creator": [],
            "director": [],
            "trailer": {
                "name": "Fool Me Once",
                "url": "https://www.youtube.com/embed/nhC8AG8cwcc?si=H8RNdanHr8y7MIZn",
                "description": "Fool Me Once",
                "duration": "PT1M53S",
                "uploadDate": "2023-12-08T13:05:02.549Z"
            }
        },
        {
            "id": "tt14998742",
            "name": "Rebel Moon - Part One: A Child of Fire",
            "image": "https://m.media-amazon.com/images/M/MV5BYzlhNzBmYjUtNjRmZC00MDg3LWE4NDMtZDNjODUwNTljMzhlXkEyXkFqcGdeQXVyODk4OTc3MTY@._V1_.jpg",
            "description": "When a peaceful settlement on the edge of a distant moon finds itself threatened by the armies of a tyrannical ruling force, a mysterious stranger living among its villagers becomes their best hope for survival.",
            "review": {
                "reviewRating": {
                    "worstRating": 1,
                    "bestRating": 10,
                    "ratingValue": 6
                }
            },
            "genre": [
                "Action",
                "Adventure",
                "Drama"
            ],
            "trailer": {
                "name": "Watch Now on Netflix",
                "url": "https://www.youtube.com/embed/fhr3MzT6exg?si=M1JITL473g1zL1pa",
                "description": "From Zack Snyder, the filmmaker behind 300, Man of Steel, and Army of the Dead, comes REBEL MOON, a 2-part movie event decades in the making.\n\nAfter crash landing on a moon in the furthest reaches of the universe, Kora (Sofia Boutella), a stranger with a mysterious past, begins a new life among a peaceful settlement of farmers. But she soon becomes their only hope for survival when the tyrannical Regent Balisarius (Fra Fee) and his cruel emissary, Admiral Noble (Ed Skrein), discover the farmers have unwittingly sold their crops to the Bloodaxes (Cleopatra Coleman and Ray Fisher)--leaders of a fierce group of insurgents hunted by the Motherworld.",
                "duration": "PT2M49S",
                "uploadDate": "2023-11-12T21:44:10.793Z"
            },
            "actor": [
                {
                    "id": "nm1154749",
                    "name": "Sofia Boutella"
                },
                {
                    "id": "nm0005023",
                    "name": "Djimon Hounsou"
                },
                {
                    "id": "nm4534098",
                    "name": "Ed Skrein"
                }
            ],
            "director": [
                {
                    "id": "nm0811583",
                    "name": "Zack Snyder"
                }
            ],
            "creator": [
                {
                    "id": "nm0811583",
                    "name": "Zack Snyder"
                },
                {
                    "id": "nm0426500",
                    "name": "Kurt Johnstad"
                },
                {
                    "id": "nm8748334",
                    "name": "Shay Hatten"
                }
            ]
        },
        {
            "id": "tt2802850",
            "name": "Fargo",
            "image": "https://m.media-amazon.com/images/M/MV5BMjNlMTIxNDEtY2U3OC00ZGFlLTgxNzEtZDU3NTdiZTAzN2MxXkEyXkFqcGdeQXVyMTU1ODIwMTM1._V1_.jpg",
            "description": "Various chronicles of deception, intrigue, and murder in and around frozen Minnesota. All of these tales mysteriously lead back one way or another to Fargo, North Dakota.",
            "review": {
                "reviewRating": {
                    "worstRating": 1,
                    "bestRating": 10,
                    "ratingValue": 9
                }
            },
            "genre": [
                "Crime",
                "Drama",
                "Thriller"
            ],
            "actor": [
                {
                    "id": "nm0000671",
                    "name": "Billy Bob Thornton"
                },
                {
                    "id": "nm0293509",
                    "name": "Martin Freeman"
                },
                {
                    "id": "nm2798112",
                    "name": "Allison Tolman"
                }
            ],
            "creator": [
                {
                    "id": "nm1279638",
                    "name": "Noah Hawley"
                }
            ],
            "director": [],
            "trailer": {
                "name": "Finale Trailer - Season 5",
                "url": "https://www.youtube.com/embed/setgvHG3w48?si=z7FhsyWgfjhP1CXR",
                "description": "Various chronicles of deception, intrigue, and murder in and around frozen Minnesota. All of these tales mysteriously lead back one way or another to Fargo, North Dakota.",
                "duration": "PT31S",
                "uploadDate": "2024-01-12T14:38:00.177Z"
            }
        },
        {
            "id": "tt14230458",
            "name": "Poor Things",
            "image": "https://m.media-amazon.com/images/M/MV5BNGIyYWMzNjktNDE3MC00YWQyLWEyMmEtN2ZmNzZhZDk3NGJlXkEyXkFqcGdeQXVyMTUzMTg2ODkz._V1_.jpg",
            "description": "The incredible tale about the fantastical evolution of Bella Baxter; a young woman brought back to life by the brilliant and unorthodox scientist, Dr. Godwin Baxter.",
            "review": {
                "reviewRating": {
                    "worstRating": 1,
                    "bestRating": 10,
                    "ratingValue": 9
                }
            },
            "genre": [
                "Comedy",
                "Drama",
                "Romance"
            ],
            "trailer": {
                "name": "Extended Look Trailer",
                "url": "https://www.youtube.com/embed/vjm0udI77KU?si=pog_E34qZk-NC0YZ",
                "description": "The incredible tale about the fantastical evolution of Bella Baxter, a young woman brought back to life by the brilliant and unorthodox scientist Dr. Godwin Baxter.",
                "duration": "PT1M5S",
                "uploadDate": "2023-10-19T14:06:01.622Z"
            },
            "actor": [
                {
                    "id": "nm1297015",
                    "name": "Emma Stone"
                },
                {
                    "id": "nm0749263",
                    "name": "Mark Ruffalo"
                },
                {
                    "id": "nm0000353",
                    "name": "Willem Dafoe"
                }
            ],
            "director": [
                {
                    "id": "nm0487166",
                    "name": "Yorgos Lanthimos"
                }
            ],
            "creator": [
                {
                    "id": "nm1110111",
                    "name": "Tony McNamara"
                },
                {
                    "id": "nm1206865",
                    "name": "Alasdair Gray"
                }
            ]
        },
        {
            "id": "tt12324366",
            "name": "Percy Jackson and the Olympians",
            "image": "https://m.media-amazon.com/images/M/MV5BMTYyNGUyNWMtMWFlMy00NThiLTk3YjItMWE2MzMzNmQwZTU3XkEyXkFqcGdeQXVyMTkxNjUyNQ@@._V1_.jpg",
            "description": "Demigod Percy Jackson leads a quest across America to prevent a war among the Olympian gods.",
            "review": {
                "reviewRating": {
                    "worstRating": 1,
                    "bestRating": 10,
                    "ratingValue": 9
                }
            },
            "genre": [
                "Action",
                "Adventure",
                "Family"
            ],
            "actor": [
                {
                    "id": "nm11880640",
                    "name": "Walker Scobell"
                },
                {
                    "id": "nm7122558",
                    "name": "Leah Jeffries"
                },
                {
                    "id": "nm5619095",
                    "name": "Aryan Simhadri"
                }
            ],
            "creator": [
                {
                    "id": "nm2292894",
                    "name": "Rick Riordan"
                },
                {
                    "id": "nm2379544",
                    "name": "Jonathan E. Steinberg"
                }
            ],
            "director": [],
            "trailer": {
                "name": "Now Streaming",
                "url": "https://www.youtube.com/embed/bzHMAXqFFvc?si=t-5JQrt0ImXXQvVP",
                "description": "Demigod Percy Jackson leads a quest across America to prevent a war among the Olympian gods.",
                "duration": "PT2M23S",
                "uploadDate": "2023-12-11T21:48:51.626Z"
            }
        },
        {
            "id": "tt12747748",
            "name": "Leave the World Behind",
            "image": "https://m.media-amazon.com/images/M/MV5BMTUzM2I3NDEtMjNhYi00NTQ0LThmZDItZTMyMzM2MjJmZGRjXkEyXkFqcGdeQXVyMTU3NDU4MDg2._V1_.jpg",
            "description": "A familys getaway to a luxurious rental home takes an ominous turn when a cyberattack knocks out their devices, and two strangers appear at their door.",
            "review": {
                "reviewRating": {
                    "worstRating": 1,
                    "bestRating": 10,
                    "ratingValue": 6
                }
            },
            "genre": [
                "Drama",
                "Mystery",
                "Thriller"
            ],
            "trailer": {
                "name": "Final Trailer",
                "url": "https://www.youtube.com/embed/nV8j2bf3gys?si=TJM_uL088DKalyzC",
                "description": "A familys getaway to a luxurious rental home takes an ominous turn when a cyberattack knocks out their devices, and two strangers appear at their door.",
                "duration": "PT1M1S",
                "uploadDate": "2023-12-04T15:33:59.750Z"
            },
            "actor": [
                {
                    "id": "nm0000210",
                    "name": "Julia Roberts"
                },
                {
                    "id": "nm0991810",
                    "name": "Mahershala Ali"
                },
                {
                    "id": "nm0000160",
                    "name": "Ethan Hawke"
                }
            ],
            "director": [
                {
                    "id": "nm1322753",
                    "name": "Sam Esmail"
                }
            ],
            "creator": [
                {
                    "id": "nm11753223",
                    "name": "Rumaan Alam"
                },
                {
                    "id": "nm1322753",
                    "name": "Sam Esmail"
                }
            ]
        },
        {
            "id": "tt6166392",
            "name": "Wonka",
            "image": "https://m.media-amazon.com/images/M/MV5BNDM4NTk0NjktZDJhMi00MmFmLTliMzEtN2RkZDY2OTNiMDgzXkEyXkFqcGdeQXVyMTUzMTg2ODkz._V1_.jpg",
            "description": "With dreams of opening a shop in a city renowned for its chocolate, a young and poor Willy Wonka discovers that the industry is run by a cartel of greedy chocolatiers.",
            "review": {
                "reviewRating": {
                    "worstRating": 1,
                    "bestRating": 10,
                    "ratingValue": 9
                }
            },
            "genre": [
                "Adventure",
                "Comedy",
                "Family"
            ],
            "trailer": {
                "name": "Book Tickets Now",
                "url": "https://www.youtube.com/embed/otNh9bTjXWg?si=UWmaKsBaKXima9EP",
                "description": "Based on the extraordinary character at the center of Charlie and the Chocolate Factory, Wonka tells the wondrous story of how the worlds greatest inventor, magician and chocolate-maker became the beloved Willy Wonka we know today.",
                "duration": "PT2M42S",
                "uploadDate": "2023-11-27T15:51:30.207Z"
            },
            "actor": [
                {
                    "id": "nm3154303",
                    "name": "Timothée Chalamet"
                },
                {
                    "id": "nm15067637",
                    "name": "Gustave Die"
                },
                {
                    "id": "nm0564133",
                    "name": "Murray McArthur"
                }
            ],
            "director": [
                {
                    "id": "nm1653753",
                    "name": "Paul King"
                }
            ],
            "creator": [
                {
                    "id": "nm1375030",
                    "name": "Simon Farnaby"
                },
                {
                    "id": "nm1653753",
                    "name": "Paul King"
                },
                {
                    "id": "nm0001094",
                    "name": "Roald Dahl"
                }
            ]
        }
    ],
    "name": [
        {
            "id": "nm1154749",
            "name": "Sofia Boutella",
            "image": "https://resizing.flixster.com/-XZAfHZM39UwaGJIFWKAE8fS0ak=/v3/t/v9/AllPhotos/327103/327103_v9_bb.jpg",
            "description": "Sofia Boutella. Actress: Kingsman: The Secret Service. Sofia Boutella is an Algerian actress, dancer and model. She was born in the Bab El Oued district of Algiers in Algeria, the daughter of composer and jazz musician Safy Boutella, and an architect mother. She started classical dance education when she was five years old. In 1992, at age 10, she left Algeria with her family and moved to France, where she...",
            "video": {
                "name": "Go Inside Zack Snyders &quot;Robot Genius&quot; Brain in Rebel Moon",
                "url": "https://www.youtube.com/embed/d9SnnkiO9r0?si=u1Lg9-E6D6G4l2jQ",
                "description": "Rebel Moon - Part One: A Child of Fire stars Sofia Boutella, Ed Skrein, Cleopatra Coleman, Ray Fisher, Charlie Hunnam, Michiel Huisman, Djimon Hounsou, Staz Nair, and E. Duffy dive deep into filmmaker Zack Snyders creative process on the fantastical space saga, tease a little about what to expect from the upcoming R-rated extended version of the movie, and offer an off-the-cuff impression of the director.",
                "duration": "PT3M40S",
                "uploadDate": "2023-12-19T21:38:55Z"
            },
            "headline": "Sofia Boutella - Actress, Soundtrack",
            "mainEntity": {
                "id": "nm1154749",
                "name": "Sofia Boutella",
                "image": "https://m.media-amazon.com/images/M/MV5BMzU4ODM4MTQzMl5BMl5BanBnXkFtZTgwNTk5NzkxNTM@._V1_.jpg",
                "description": "Sofia Boutella. Actress: Kingsman: The Secret Service. Sofia Boutella is an Algerian actress, dancer and model. She was born in the Bab El Oued district of Algiers in Algeria, the daughter of composer and jazz musician Safy Boutella, and an architect mother. She started classical dance education when she was five years old. In 1992, at age 10, she left Algeria with her family and moved to France, where she...",
                "jobTitle": [
                    "Actress",
                    "Soundtrack"
                ],
                "birthDate": "April 03, 1982",
                "age": 42
            }
        },
        {
            "id": "nm0005023",
            "name": "Djimon Hounsou",
            "image": "https://m.media-amazon.com/images/M/MV5BMjQ2NTM4MzI4M15BMl5BanBnXkFtZTcwOTkxMjcxNA@@._V1_.jpg",
            "description": "Djimon Hounsou. Actor: Blood Diamond. Djimon Hounsou was born in Cotonou, Benin, in west Africa to Albertine and Pierre Hounsou, a cook. He moved to Lyon, France, when he was 13. Hounsou has graced the catwalks of Paris and London as a popular male model. He has since left his modeling career and has worked on Gladiator (2000) by Ridley Scott and Amistad (1997) by Steven Spielberg.",
            "video": {
                "name": "Go Inside Zack Snyders &quot;Robot Genius&quot; Brain in Rebel Moon",
                "url": "https://www.youtube.com/embed/6cWCB9QEDMA?si=Q9J1b7g54kEJX5u8",
                "description": "Rebel Moon - Part One: A Child of Fire stars Sofia Boutella, Ed Skrein, Cleopatra Coleman, Ray Fisher, Charlie Hunnam, Michiel Huisman, Djimon Hounsou, Staz Nair, and E. Duffy dive deep into filmmaker Zack Snyders creative process on the fantastical space saga, tease a little about what to expect from the upcoming R-rated extended version of the movie, and offer an off-the-cuff impression of the director.",
                "duration": "PT3M40S",
                "uploadDate": "2023-12-19T21:38:55Z"
            },
            "headline": "Djimon Hounsou - Actor, Producer, Director",
            "mainEntity": {
                "id": "nm0005023",
                "name": "Djimon Hounsou",
                "image": "https://m.media-amazon.com/images/M/MV5BMjQ2NTM4MzI4M15BMl5BanBnXkFtZTcwOTkxMjcxNA@@._V1_.jpg",
                "description": "Djimon Hounsou. Actor: Blood Diamond. Djimon Hounsou was born in Cotonou, Benin, in west Africa to Albertine and Pierre Hounsou, a cook. He moved to Lyon, France, when he was 13. Hounsou has graced the catwalks of Paris and London as a popular male model. He has since left his modeling career and has worked on Gladiator (2000) by Ridley Scott and Amistad (1997) by Steven Spielberg.",
                "jobTitle": [
                    "Actor",
                    "Producer",
                    "Director"
                ],
                "birthDate": "April 24, 1964",
                "age": 60
            }
        },
        {
            "id": "nm4534098",
            "name": "Ed Skrein",
            "image": "https://encrypted-tbn2.gstatic.com/licensed-image?q=tbn:ANd9GcSD_3UXQJngFXVi70u8pFkqjSsrdqo8huhXCHnOkAUUH6eNFFtogHILZolZ4lp8HMAUkYU77HWceh0gByE",
            "description": "Ed Skrein. Actor: Deadpool. Ed Skrein grew up in North London, graduated with a degree in Fine Arts from Central Saint Martins, and is one of the most highly versatile artists of his generation. He was selected by Screen International as one of their &quot;Stars of Tomorrow&quot; in 2013, which showcases the next generation of talent from the UK.\n\nMost recently, Skrein starred as the villain Ajax in Marvels and Twentieth...",
            "video": {
                "name": "Go Inside Zack Snyders &quot;Robot Genius&quot; Brain in Rebel Moon",
                "url": "https://www.youtube.com/embed/UEkPx2kJniE?si=lIwD8i4YxAHW9p2f",
                "description": "Rebel Moon - Part One: A Child of Fire stars Sofia Boutella, Ed Skrein, Cleopatra Coleman, Ray Fisher, Charlie Hunnam, Michiel Huisman, Djimon Hounsou, Staz Nair, and E. Duffy dive deep into filmmaker Zack Snyders creative process on the fantastical space saga, tease a little about what to expect from the upcoming R-rated extended version of the movie, and offer an off-the-cuff impression of the director.",
                "duration": "PT3M40S",
                "uploadDate": "2023-12-19T21:38:55Z"
            },
            "headline": "Ed Skrein - Actor, Director, Writer",
            "mainEntity": {
                "id": "nm4534098",
                "name": "Ed Skrein",
                "image": "https://m.media-amazon.com/images/M/MV5BYThkMzU5NjItZDY1NS00NzBmLTg4ZTgtMjBiNTU3YmI2ZjQzXkEyXkFqcGdeQXVyMTkxNjUyNQ@@._V1_.jpg",
                "description": "Ed Skrein. Actor: Deadpool. Ed Skrein grew up in North London, graduated with a degree in Fine Arts from Central Saint Martins, and is one of the most highly versatile artists of his generation. He was selected by Screen International as one of their &quot;Stars of Tomorrow&quot; in 2013, which showcases the next generation of talent from the UK.\n\nMost recently, Skrein starred as the villain Ajax in Marvels and Twentieth...",
                "jobTitle": [
                    "Actor",
                    "Director",
                    "Writer"
                ],
                "birthDate": "March 29, 1983",
                "age": 41
            }
        },
        {
            "id": "nm4422686",
            "name": "Barry Keoghan",
            "image": "https://m.media-amazon.com/images/M/MV5BMTcyNzEzMjY4NV5BMl5BanBnXkFtZTgwOTMzOTA5MjI@._V1_.jpg",
            "description": "Barry came to prominence in the 2017 film 'The Killing of a Sacred Deer' with his truly terrifying portrayal of Martin,an American teenager exacting a grisly revenge on drunken surgeon Colin Farrell, but he was not an American nor a teen-ager, born in Dublin on 17th October 1992 and has a brother Eric. From the age of thirteen he was raised by a grandmother and got into acting by answering an advert for non-professionals to train at a school called the Factory. Beginning in Irish soap Fair City' he played Irish roles in the likes of '71' but in 2017 bagged the role of Martin as well as appearing in the lauded 'Dunkirk. In addition to acting Barry is a talented amateur boxer, representing the Celtic Core and is an ambassador for Dior....",
            "video": {
                "name": "Barry Keoghan | Career Retrospective",
                "url": "https://www.youtube.com/embed/m6EvhAogLFU?si=5SD9eYFRba6XfxyF",
                "description": "Take a closer look at the various roles Barry Keoghan has played throughout his acting career.",
                "duration": "PT54S",
                "uploadDate": "2021-10-02T14:29:54Z"
            },
            "headline": "Barry Keoghan - Actor, Soundtrack",
            "mainEntity": {
                "id": "nm4422686",
                "name": "Barry Keoghan",
                "image": "https://m.media-amazon.com/images/M/MV5BMTcyNzEzMjY4NV5BMl5BanBnXkFtZTgwOTMzOTA5MjI@._V1_.jpg",
                "description": "Barry Keoghan. Actor: The Killing of a Sacred Deer. Barry came to prominence in the 2017 film The Killing of a Sacred Deer with his truly terrifying portrayal of Martin,an American teenager exacting a grisly revenge on drunken surgeon Colin Farrell, but he was not an American nor a teen-ager, born in Dublin on 17th October 1992 and has a brother Eric. From the age of thirteen he was raised...",
                "jobTitle": [
                    "Actor",
                    "Soundtrack"
                ],
                "birthDate": "Octorber 18, 1992",
                "age": 32
            }
        },
        {
            "id": "nm8624059",
            "name": "Jacob Elordi",
            "image": "https://m.media-amazon.com/images/M/MV5BNDE5NGRhNzMtZTRlMC00YzY0LWEzYzMtMTU1ZjAyMTBiNDRiXkEyXkFqcGdeQXVyNzAwNTgwOTk@._V1_.jpg",
            "description": "Jacob Elordi. Actor: The Kissing Booth. Jacob Elordi was born on June 26, in Brisbane, Australia as Jacob Nathaniel Elordi. He is an actor known for Emerald Fennells Saltburn (2023), the Netflix Hit The Kissing Booth (2018), and the hit HBO A24 drama series Euphoria (2019). Other titles include 2-Hearts (2019). He grew up acting in the theatre.",
            "video": {
                "name": "The Rise of Jacob Elordi",
                "embedUrl": "https://www.imdb.com/video/imdb/vi2664417049",
                "thumbnail": {
                    "contentUrl": "https://m.media-amazon.com/images/M/MV5BMTY0YmViMTEtMWZkMy00YWZmLTkxMDQtMWU5YTVkZjYwODBmXkEyXkFqcGdeQXJoYW5uYWg@._V1_.jpg"
                },
                "thumbnailUrl": "https://m.media-amazon.com/images/M/MV5BMTY0YmViMTEtMWZkMy00YWZmLTkxMDQtMWU5YTVkZjYwODBmXkEyXkFqcGdeQXJoYW5uYWg@._V1_.jpg",
                "url": "https://www.imdb.com/video/vi2664417049/",
                "description": "Jacob Elordi returns to the big screen playing Elvis in the Sofia Coppola-directed biopic Priscilla. &quot;No Small Parts&quot; breaks down Elordis earliest roles in Australian movies and TV, The Kissing Booth movies, &quot;Euphoria,&quot; and much more. Which of Jacob Elordis roles is your favorite?",
                "duration": "PT2M25S",
                "uploadDate": "2023-10-24T21:47:13Z"
            },
            "headline": "Jacob Elordi - Actor, Writer, Producer",
            "mainEntity": {
                "id": "nm8624059",
                "name": "Jacob Elordi",
                "image": "https://m.media-amazon.com/images/M/MV5BNDE5NGRhNzMtZTRlMC00YzY0LWEzYzMtMTU1ZjAyMTBiNDRiXkEyXkFqcGdeQXVyNzAwNTgwOTk@._V1_.jpg",
                "description": "Jacob Elordi. Actor: The Kissing Booth. Jacob Elordi was born on June 26, in Brisbane, Australia as Jacob Nathaniel Elordi. He is an actor known for Emerald Fennells Saltburn (2023), the Netflix Hit The Kissing Booth (2018), and the hit HBO A24 drama series Euphoria (2019). Other titles include 2-Hearts (2019). He grew up acting in the theatre.",
                "jobTitle": [
                    "Actor",
                    "Writer",
                    "Producer"
                ],
                "birthDate": "June 26, 1997",
                "age": 27
            }
        },
        {
            "id": "nm0683253",
            "name": "Rosamund Pike",
            "image": "https://m.media-amazon.com/images/M/MV5BNDQ5MDIyMjg3NV5BMl5BanBnXkFtZTgwOTU2NTE0NDM@._V1_.jpg",
            "description": "Rosamund Pike. Actress: Gone Girl. Born in 1979 in London, England, actress Rosamund Mary Elizabeth Pike is the only child of a classical violinist mother, Caroline (Friend), and an opera singer father, Julian Pike. Due to her parents work, she spent her early childhood traveling around Europe. Pike attended Badminton School in Bristol, England and began acting at the National Youth Theatre. While appearing in a National Youth Theatre production...",
            "video": {
                "name": "The Rise of Rosamund Pike",
                "url": "https://www.youtube.com/embed/1hxIxskjW-M?si=Exrh5Tm7PpVvPADy",
                "description": "Oscar-nominated actress Rosamund Pike returns for the second season of the fantasy series &quot;The Wheel of Time.&quot; From her early work as a Bond villain and a Bennet sister in Pride and Prejudice to portraying real-life characters like Marie Curie in Radioactive, &quot;No Small Parts&quot; takes a look at her rise to fame.",
                "duration": "PT3M45S",
                "uploadDate": "2023-08-23T19:13:39Z"
            },
            "headline": "Rosamund Pike - Actress, Producer, Soundtrack",
            "mainEntity": {
                "id": "nm0683253",
                "name": "Rosamund Pike",
                "image": "https://m.media-amazon.com/images/M/MV5BNDQ5MDIyMjg3NV5BMl5BanBnXkFtZTgwOTU2NTE0NDM@._V1_.jpg",
                "description": "Rosamund Pike. Actress: Gone Girl. Born in 1979 in London, England, actress Rosamund Mary Elizabeth Pike is the only child of a classical violinist mother, Caroline (Friend), and an opera singer father, Julian Pike. Due to her parents work, she spent her early childhood traveling around Europe. Pike attended Badminton School in Bristol, England and began acting at the National Youth Theatre. While appearing in a National Youth Theatre production...",
                "jobTitle": [
                    "Actress",
                    "Producer",
                    "Soundtrack"
                ],
                "birthDate": "January 27, 1979",
                "age": 45
            }
        },
        {
            "id": "nm0035514",
            "name": "Richard Armitage",
            "image": "https://m.media-amazon.com/images/M/MV5BMTZkZDcwMzEtNmE3Ny00M2YzLWJhNDAtY2U5NjkzMzJkNjM4XkEyXkFqcGdeQXVyMjQxODUxMjA@._V1_.jpg",
            "description": "Richard Armitage. Actor: The Hobbit: An Unexpected Journey. Richard Crispin Armitage was born and raised in Leicester, England, to Margaret (Hendey), a secretary, and John Armitage, an engineer. He attended Pattison College in Binley Road, Coventry, where he discovered his love for acting. He took part in many theatre productions all over the UK, from musical theatre (Cats) to classical theatre (Death of a Salesman). He enrolled at LAMDA in...",
            "video": {
                "name": "Fool Me Once",
                "url": "https://www.youtube.com/embed/_22x27tO_XY?si=J4kejIJ6gvQ6Wvb7",
                "description": "Fool Me Once",
                "duration": "PT1M53S",
                "uploadDate": "2023-12-08T13:05:02Z"
            },
            "headline": "Richard Armitage - Actor, Producer, Writer",
            "mainEntity": {
                "id": "nm0035514",
                "name": "Richard Armitage",
                "image": "https://m.media-amazon.com/images/M/MV5BMTZkZDcwMzEtNmE3Ny00M2YzLWJhNDAtY2U5NjkzMzJkNjM4XkEyXkFqcGdeQXVyMjQxODUxMjA@._V1_.jpg",
                "description": "Richard Armitage. Actor: The Hobbit: An Unexpected Journey. Richard Crispin Armitage was born and raised in Leicester, England, to Margaret (Hendey), a secretary, and John Armitage, an engineer. He attended Pattison College in Binley Road, Coventry, where he discovered his love for acting. He took part in many theatre productions all over the UK, from musical theatre (Cats) to classical theatre (Death of a Salesman). He enrolled at LAMDA in...",
                "jobTitle": [
                    "Actor",
                    "Producer",
                    "Writer"
                ],
                "birthDate": "August 22, 1971",
                "age": 53
            }
        },
        {
            "id": "nm2253821",
            "name": "Adeel Akhtar",
            "image": "https://m.media-amazon.com/images/M/MV5BMTk2NTMwMjE2Ml5BMl5BanBnXkFtZTgwNDI5MDA1MzI@._V1_.jpg",
            "description": "Adeel Akhtar. Actor: Four Lions. Adeel was born in London on 18th September 1980 to a Pakistani father and a Kenyan mother and attended Cheltenham College throughout the 1990s. His father was keen for him to become a lawyer and he obtained a law degree but was more interested in acting and studied at the Actors Studio in New York. He has made several stage appearances, including as Guildenstern in...",
            "video": {
                "name": "Fool Me Once",
                "url": "https://www.youtube.com/embed/gW9UGSSvfJU?si=3PVO8dJJINCRuPA6",
                "description": "Fool Me Once",
                "duration": "PT1M53S",
                "uploadDate": "2023-12-08T13:05:02Z"
            },
            "headline": "Adeel Akhtar - Actor, Additional Crew, Soundtrack",
            "mainEntity": {
                "id": "nm2253821",
                "name": "Adeel Akhtar",
                "image": "https://m.media-amazon.com/images/M/MV5BMTk2NTMwMjE2Ml5BMl5BanBnXkFtZTgwNDI5MDA1MzI@._V1_.jpg",
                "description": "Adeel Akhtar. Actor: Four Lions. Adeel was born in London on 18th September 1980 to a Pakistani father and a Kenyan mother and attended Cheltenham College throughout the 1990s. His father was keen for him to become a lawyer and he obtained a law degree but was more interested in acting and studied at the Actors Studio in New York. He has made several stage appearances, including as Guildenstern in...",
                "jobTitle": [
                    "Actor",
                    "Additional Crew",
                    "Soundtrack"
                ],
                "birthDate": "September 18, 1980",
                "age": 44
            }
        },
        {
            "id": "nm3154303",
            "name": "Timothée Chalamet",
            "image": "https://m.media-amazon.com/images/M/MV5BNThiOTM4NTAtMDczNy00YzlkLWJhNTEtZTZhNDVmYzlkZWI0XkEyXkFqcGdeQXVyMTEyMjM2NDc2._V1_.jpg",
            "description": "Timothée Chalamet. Actor: Call Me by Your Name. Timothée Hal Chalamet was born in Manhattan, to Nicole Flender, a real estate broker and dancer, and Marc Chalamet, a UNICEF editor. His mother, who is from New York, is Jewish, of Russian Jewish and Austrian Jewish descent. His father, who is from Nîmes, France, is of French and English ancestry. He is the brother of actress Pauline Chalamet, a nephew of...",
            "video": {
                "name": "How Timothée Chalamet and the Wonka Cast Cracked Each Other Up",
                "embedUrl": "https://www.imdb.com/video/imdb/vi856213273",
                "thumbnail": {
                    "contentUrl": "https://m.media-amazon.com/images/M/MV5BMzM4ZDAxNTktNTIxYy00YmQ5LWJlMGEtOWU0YzExYjAxMTk5XkEyXkFqcGdeQWplZmZscA@@._V1_.jpg"
                },
                "thumbnailUrl": "https://m.media-amazon.com/images/M/MV5BMzM4ZDAxNTktNTIxYy00YmQ5LWJlMGEtOWU0YzExYjAxMTk5XkEyXkFqcGdeQWplZmZscA@@._V1_.jpg",
                "url": "https://www.imdb.com/video/vi856213273/",
                "description": "Stars Timothée Chalamet, Keegan-Michael Key, Natasha Rothwell, and Calah Lane join director Paul King to remember all the chocolatey chortles they shared on the set of Wonka. Plus find out what Keegan really thought of Timothées latest &quot;Saturday Night Live&quot; hosting appearance.",
                "duration": "PT2M55S",
                "uploadDate": "2023-12-14T02:21:49Z"
            },
            "headline": "Timothée Chalamet - Actor, Producer, Soundtrack",
            "mainEntity": {
                "id": "nm3154303",
                "name": "Timothée Chalamet",
                "image": "https://m.media-amazon.com/images/M/MV5BNThiOTM4NTAtMDczNy00YzlkLWJhNTEtZTZhNDVmYzlkZWI0XkEyXkFqcGdeQXVyMTEyMjM2NDc2._V1_.jpg",
                "description": "Timothée Chalamet. Actor: Call Me by Your Name. Timothée Hal Chalamet was born in Manhattan, to Nicole Flender, a real estate broker and dancer, and Marc Chalamet, a UNICEF editor. His mother, who is from New York, is Jewish, of Russian Jewish and Austrian Jewish descent. His father, who is from Nîmes, France, is of French and English ancestry. He is the brother of actress Pauline Chalamet, a nephew of...",
                "jobTitle": [
                    "Actor",
                    "Producer",
                    "Soundtrack"
                ],
                "birthDate": "December 27, 1995",
                "age": 29
            }
        },
        {
            "id": "nm0564133",
            "name": "Murray McArthur",
            "image": "https://m.media-amazon.com/images/M/MV5BMTUxNjU4NjQ3MV5BMl5BanBnXkFtZTgwNjYwMjEyNzE@._V1_.jpg",
            "description": "Murray McArthur. Actor: Wednesday. Best known for Game of Thrones in which he plays the Wildling chieftain, Dim Dalba. A British stage, television and film actor. The son of a mushroom farmer, of Scottish parentage and red-haired, he was born and raised in Devon. He received a BA (Joint Hons) degree in English and Drama at Loughborough University and went on to study acting at the Drama Studio London.",
            "video": {
                "name": "Murray McArthur - Showreel",
                "embedUrl": "https://www.imdb.com/video/imdb/vi4276667673",
                "thumbnail": {
                    "contentUrl": "https://m.media-amazon.com/images/M/MV5BNjEzOTljOGEtNzYzNC00MDdlLWI0NWMtMzMwZmIyMGQwMDAwXkEyXkFqcGdeQXRyYW5zY29kZS13b3JrZmxvdw@@._V1_.jpg"
                },
                "thumbnailUrl": "https://m.media-amazon.com/images/M/MV5BNjEzOTljOGEtNzYzNC00MDdlLWI0NWMtMzMwZmIyMGQwMDAwXkEyXkFqcGdeQXRyYW5zY29kZS13b3JrZmxvdw@@._V1_.jpg",
                "url": "https://www.imdb.com/video/vi4276667673/",
                "description": "Clips featuring Murray McArthur in Wednesday (Netflix), Game of Thrones (HBO) and Marooned Awakening (Across The Channel).",
                "duration": "PT9M29S",
                "uploadDate": "2022-12-18T13:34:46Z"
            },
            "headline": "Murray McArthur - Actor",
            "mainEntity": {
                "id": "nm0564133",
                "name": "Murray McArthur",
                "image": "https://m.media-amazon.com/images/M/MV5BMTUxNjU4NjQ3MV5BMl5BanBnXkFtZTgwNjYwMjEyNzE@._V1_.jpg",
                "description": "Murray McArthur. Actor: Wednesday. Best known for Game of Thrones in which he plays the Wildling chieftain, Dim Dalba. A British stage, television and film actor. The son of a mushroom farmer, of Scottish parentage and red-haired, he was born and raised in Devon. He received a BA (Joint Hons) degree in English and Drama at Loughborough University and went on to study acting at the Drama Studio London.",
                "jobTitle": [
                    "Actor"
                ],
                "birthDate": "May 04, 1966",
                "age": 58
            }
        },
        {
            "id": "nm2193504",
            "name": "Emerald Fennell",
            "image":"https://m.media-amazon.com/images/M/MV5BYmU4YWNlZmUtNTAwMi00N2JhLTkxZGYtNzkzYjZmMmUyY2U0XkEyXkFqcGdeQXVyMjMyMDMyNjI@._V1_.jpg",
            "description": "Emerald Lilly Fennell is an English actress, filmmaker, and writer. She has received many awards and nominations, including an Academy Award, two British Academy Film Awards, one Screen Actors Guild Award, and nominations for three Primetime Emmy Awards and three Golden Globe Awards. Fennell first gained attention for her roles in period drama films, such as Albert Nobbs (2011), Anna Karenina (2012), The Danish Girl (2015), and Vita and Virginia (2018). She went on to receive wider recognition for her starring roles in the BBC One period drama series Call the Midwife (2013-17) and for her portrayal of Camilla, Duchess of Cornwall in the Netflix period drama series The Crown (2019-20).",
            "video": {
                "name": "Emerald Fennell - Actor,Director,Priducer",
                "url": "https://www.youtube.com/embed/1DiVSbgPcAo?si=Ubs2EFixTZcuEQEY"
            },
            "headline": "Emerald Fennell - Actor,Director,Priducer",
            "mainEntity": {
                "id": "nm2193504",
                "name": "Emerald Fennell",
                "image": "https://m.media-amazon.com/images/M/MV5BYmU4YWNlZmUtNTAwMi00N2JhLTkxZGYtNzkzYjZmMmUyY2U0XkEyXkFqcGdeQXVyMjMyMDMyNjI@._V1_.jpg",
                "description": "Emerald Lilly Fennell is an English actress, filmmaker, and writer. She has received many awards and nominations, including an Academy Award, two British Academy Film Awards, one Screen Actors Guild Award, and nominations for three Primetime Emmy Awards and three Golden Globe Awards. Fennell first gained attention for her roles in period drama films, such as Albert Nobbs (2011), Anna Karenina (2012), The Danish Girl (2015), and Vita and Virginia (2018). She went on to receive wider recognition for her starring roles in the BBC One period drama series Call the Midwife (2013-17) and for her portrayal of Camilla, Duchess of Cornwall in the Netflix period drama series The Crown (2019-20).",
                "jobTitle": [
                    "Actor",
                    "Director",
                    "Producer"
                ],
                "birthDate": "Octorber 1, 1985",
                "age": 38
            }
        },
        {
            "id": "nm2882021",
            "name": "Michelle Keegan",
            "image":"https://m.media-amazon.com/images/M/MV5BMTY0MDc0MDAzNF5BMl5BanBnXkFtZTcwOTIyNjIyOA@@._V1_.jpg",
            "description": "Michelle Keegan was born on June 3, 1987 in Stockport, Greater Manchester, England, UK. She is an actress, known for Coronation Street (1960), Our Girl (2013) and Drunk History: UK (2015). She has been married to Mark Wright since May 24, 2015.",
            "video": {
                "name": "Michelle Keegan - Actress",
                "url": "https://www.youtube.com/embed/nUN_kFZgBvo?si=J0-fMGlQ6831zXYH"
            },
            "mainEntity": {
                "id": "nm2882021",
                "name": "Michelle Keegan",
                "image": "https://m.media-amazon.com/images/M/MV5BMTY0MDc0MDAzNF5BMl5BanBnXkFtZTcwOTIyNjIyOA@@._V1_.jpg",
                "description": "Michelle Keegan was born on June 3, 1987 in Stockport, Greater Manchester, England, UK. She is an actress, known for Coronation Street (1960), Our Girl (2013) and Drunk History: UK (2015). She has been married to Mark Wright since May 24, 2015.",
                "jobTitle": [
                    "Actress"
                ],
                "birthDate": "June 3, 1987",
                "age": 36
            }
        },
        {
            "id": "nm0811583",
            "name": "Zack Snyder",
            "image":"https://m.media-amazon.com/images/M/MV5BMTMzMjUyNjk1MV5BMl5BanBnXkFtZTcwMDc2Mzk3NA@@._V1_.jpg",
            "description": "Zachary Edward 'Zack' Snyder (born March 1, 1966) is an American film director, film producer, and screenwriter, best known for action and science fiction films. Snyder made his feature film debut with the 2004 remake Dawn of the Dead and has gone on to be known for his comic book movies and superhero films, including 300 (2007), Watchmen (2009), Man of Steel (2013) and its upcoming sequel, Batman v Superman: Dawn of Justice (2016). Snyder is the co-founder of Cruel and Unusual Films, a production company he established in 2004, alongside his wife Deborah Snyder and producing partner Wesley Coller.",
            "video": {
                "name": "Zack Snyder - Director, Producer, Writer",
                "url": "https://www.youtube.com/embed/xu8SB_xte9M?si=t0uNBZqSqwEz3sN6"
            },
            "mainEntity": {
                "id": "nm0811583",
                "name": "Zack Snyder",
                "image": "https://m.media-amazon.com/images/M/MV5BMTMzMjUyNjk1MV5BMl5BanBnXkFtZTcwMDc2Mzk3NA@@._V1_.jpg",
                "description": "Zachary Edward 'Zack' Snyder (born March 1, 1966) is an American film director, film producer, and screenwriter, best known for action and science fiction films. Snyder made his feature film debut with the 2004 remake Dawn of the Dead and has gone on to be known for his comic book movies and superhero films, including 300 (2007), Watchmen (2009), Man of Steel (2013) and its upcoming sequel, Batman v Superman: Dawn of Justice (2016). Snyder is the co-founder of Cruel and Unusual Films, a production company he established in 2004, alongside his wife Deborah Snyder and producing partner Wesley Coller.",
                "jobTitle": [
                    "Director",
                    "Producer",
                    "Writer"
                ],
                "birthDate": "March 1, 1966",
                "age": 57
            }
        },
        {
            "id": "nm0426500",
            "name": "Kurt Johnstad",
            "image":"https://encrypted-tbn1.gstatic.com/licensed-image?q=tbn:ANd9GcQFIqJiKpUsdxcrhSzJwEnQ04qoA-pO8334eu0u4P9JyFqSRRV8MIg2Lne97OzntD52mZ18ONoIHUZcIi0",
            "description": "A former assistant director and key grip, Kurt Johnstad has an long-standing relationship with the military, and wrote the 'Navy SEALs playing themselves' movie, 'Act of Valor'. But he is perhaps best known for writing the cult-classic film '300', as well as it's sequel, '300: Rise of an Empire' with Zack Snyder.",
            "video": {
                "name": "Kurt Johnstad",
                "url": "https://www.youtube.com/embed/NXVWkiRrc7E?si=eL4PXgoDrJD4VZDM"
            },
            "mainEntity": {
                "id": "nm0426500",
                "name": "Kurt Johnstad",
                "image": "https://encrypted-tbn1.gstatic.com/licensed-image?q=tbn:ANd9GcQFIqJiKpUsdxcrhSzJwEnQ04qoA-pO8334eu0u4P9JyFqSRRV8MIg2Lne97OzntD52mZ18ONoIHUZcIi0",
                "description": "A former assistant director and key grip, Kurt Johnstad has an long-standing relationship with the military, and wrote the 'Navy SEALs playing themselves' movie, 'Act of Valor'. But he is perhaps best known for writing the cult-classic film '300', as well as it's sequel, '300: Rise of an Empire' with Zack Snyder.",
                "jobTitle": [
                    "Writer",
                    "Producer",
                    "Camera and Electrical Department"
                ]
            }
        },
        {
            "id": "nm8748334",
            "name": "Shay Hatten",
            "image":"https://m.media-amazon.com/images/M/MV5BN2Y2MjA1NTMtN2IxZi00ODdjLWI5MWMtMjhmYzk1YzllYWJjXkEyXkFqcGdeQXVyOTYwNjg2MTQ@._V1_.jpg",
            "description": "Shay Hatten was born on March 18, 1994 in Oakland, California, USA. He is a writer and producer, known for Rebel Moon - Part One: A Child of Fire (2023), Army of the Dead (2021) and Army of Thieves (2021).",
            "video": {
                "name": "Shay Hatten",
                "url": "https://www.youtube.com/embed/DCAUgfs6EiQ?si=uonnIwYqGwN7pFFU"
            },
            "mainEntity": {
                "id": "nm8748334",
                "name": "Shay Hatten",
                "image": "https://m.media-amazon.com/images/M/MV5BN2Y2MjA1NTMtN2IxZi00ODdjLWI5MWMtMjhmYzk1YzllYWJjXkEyXkFqcGdeQXVyOTYwNjg2MTQ@._V1_.jpg",
                "description": "Shay Hatten was born on March 18, 1994 in Oakland, California, USA. He is a writer and producer, known for Rebel Moon - Part One: A Child of Fire (2023), Army of the Dead (2021) and Army of Thieves (2021).",
                "jobTitle": [
                    "Writer",
                    "Producer"
                ],
                "birthDate": "March 18, 1994",
                "age": 29
            }
        }
    ]
}